django_advance_dumpdata/__init__.py
django_advance_dumpdata/management/__init__.py
django_advance_dumpdata/management/commands/__init__.py
django_advance_dumpdata/management/commands/dumpdata_advance.py
django_advance_dumpdata-0.0.2.dist-info/LICENCE
django_advance_dumpdata-0.0.2.dist-info/METADATA
django_advance_dumpdata-0.0.2.dist-info/WHEEL
django_advance_dumpdata-0.0.2.dist-info/top_level.txt
django_advance_dumpdata-0.0.2.dist-info/RECORD
