Metadata-Version: 2.1
Name: django-advance-dumpdata
Version: 0.0.2
Summary: Django Manage Command; Output the contents of the database as a fixture of the given format,filter and more features 
Home-page: https://github.com/EhsanSafir/django_dumpdata_advance
Author: Ehsan Safir , Sayed Farid Qattali
Author-email: EhsanSafir@outlook.com , eng.faridqattali@gmail.com 
License: UNKNOWN
Platform: UNKNOWN
Classifier: Environment :: Web Environment
Classifier: Framework :: Django
Classifier: Framework :: Django :: 2.2
Classifier: Framework :: Django :: 3.0
Classifier: Framework :: Django :: 3.1
Classifier: Framework :: Django :: 3.2
Classifier: Intended Audience :: Developers
Classifier: License :: OSI Approved :: MIT License
Classifier: Operating System :: OS Independent
Classifier: Programming Language :: Python
Classifier: Topic :: Software Development :: Libraries :: Python Modules
Classifier: Programming Language :: Python
Classifier: Programming Language :: Python :: 3
Classifier: Programming Language :: Python :: 3.6
Classifier: Programming Language :: Python :: 3.7
Classifier: Programming Language :: Python :: 3.8
Classifier: Programming Language :: Python :: 3.9
Classifier: Topic :: Utilities
Requires-Python: >=3.6
License-File: LICENCE
Requires-Dist: Django (>=2.2)
